<?xml version="1.0" encoding="UTF-8"?>
<objects serializationModel="Studio.02.00.00">
	<object class="AudioFile" id="{08c13084-aabd-4a15-96e8-0a6623d82b5c}">
		<property name="assetPath">
			<value>TO DELETE/FootSteps/WAV/Footsteps_Casual_Metal_08.wav</value>
		</property>
		<property name="frequencyInKHz">
			<value>44.0999985</value>
		</property>
		<property name="channelCount">
			<value>2</value>
		</property>
		<property name="length">
			<value>0.3287981859410431</value>
		</property>
		<relationship name="masterAssetFolder">
			<destination>{df2ffc5f-93bf-4f46-b876-4c9724a5f8f8}</destination>
		</relationship>
	</object>
</objects>
